pyams_elastic/__init__.py
pyams_elastic/client.py
pyams_elastic/include.py
pyams_elastic/interfaces.py
pyams_elastic/mixin.py
pyams_elastic/query.py
pyams_elastic/result.py
pyams_elastic/doctests/README.rst
pyams_elastic/locales/pyams_elastic.pot
pyams_elastic/locales/fr/LC_MESSAGES/pyams_elastic.mo
pyams_elastic/locales/fr/LC_MESSAGES/pyams_elastic.po
pyams_elastic/task/__init__.py
pyams_elastic/task/interfaces.py
pyams_elastic/task/zmi/__init__.py
pyams_elastic/tests/__init__.py
pyams_elastic/tests/data.py
pyams_elastic/tests/test_client.py
pyams_elastic/tests/test_functional.py
pyams_elastic/tests/test_mapping.py
pyams_elastic/tests/test_pyramid.py
pyams_elastic/tests/test_result.py
pyams_elastic/tests/test_task.py
pyams_elastic/tests/test_transaction.py
pyams_elastic/tests/test_utilsdocs.py
pyams_elastic/tests/test_utilsdocstrings.py
pyams_elastic-2.1.1.dist-info/LICENSE
pyams_elastic-2.1.1.dist-info/METADATA
pyams_elastic-2.1.1.dist-info/WHEEL
pyams_elastic-2.1.1.dist-info/namespace_packages.txt
pyams_elastic-2.1.1.dist-info/top_level.txt
pyams_elastic-2.1.1.dist-info/RECORD
