Metadata-Version: 2.1
Name: pyams-elastic
Version: 2.1.1
Summary: PyAMS integration package for Elasticsearch
Home-page: https://pyams.readthedocs.io
Author: Thierry Florac
Author-email: tflorac@ulthar.net
License: ZPL
Keywords: Pyramid PyAMS
Classifier: License :: OSI Approved :: Zope Public License
Classifier: Development Status :: 4 - Beta
Classifier: Programming Language :: Python
Classifier: Framework :: Pyramid
Classifier: Topic :: Software Development :: Libraries :: Python Modules
License-File: LICENSE
Requires-Dist: setuptools
Requires-Dist: elasticsearch
Requires-Dist: elasticsearch-dsl
Requires-Dist: persistent
Requires-Dist: pyams-utils >=2.7.6
Requires-Dist: pyramid
Requires-Dist: transaction
Requires-Dist: zope.component
Requires-Dist: zope.interface
Requires-Dist: zope.schema
Provides-Extra: test
Requires-Dist: sqlalchemy ; extra == 'test'
Requires-Dist: pyams-scheduler >=2.7.0 ; extra == 'test'
Requires-Dist: pyams-zmi ; extra == 'test'
Requires-Dist: pyramid-tm ; extra == 'test'
Requires-Dist: pyramid-zcml ; extra == 'test'
Requires-Dist: webtest ; extra == 'test'
Requires-Dist: zope.exceptions ; extra == 'test'
Requires-Dist: zope.testrunner ; extra == 'test'
